[
  {
    "name": "4/30 早",
    "prices":	{
      "天父将军":  24444,
      "辣椒":  67,
      "潮流自热饭":  95,
      "新型爆竹": 96,
      "太虚山雪糕": 69,
      "包菜": 82,
      "扩音音响": 824,
      "文物玩具": 1121,
      "古董花瓶": 1163,
      "熊熊玩偶": 1074,
      "登山杖": 1051,
      "赤鸢手办": 999
    },
    "events": [],
    "news": [
      "绿色有益健康！天命护眼日，德莉莎主教带头呼吁民众补充绿色。",
      "旅游旺季将至，知名景区太虚山计划推出文创新产品。"
    ]
  },
  {
    "name": "4/30 晚",
    "prices":	{
      "智慧眼罩":  26444,
      "辣椒":  56,
      "算命道具包":  59,
      "新型爆竹": 73,
      "墨镜": 81,
      "绿茶": 115,
      "神州运动服": 848,
      "不识时务（棉质）": 661,
      "《职场躺平500年》": 1047,
      "熊熊玩偶": 1359,
      "夜衔烛（木制）": 1348,
      "翡翠": 1337,
      "赤鸢手办": 1133,
      "包菜": 154
    },
    "events": [
      {
        "affect": ["包菜"],
        "increase": true,
        "description": "包菜成为护眼产品，居民积极采购。"
      },
      {
        "affect": ["太虚山雪糕"],
        "increase": true,
        "description": "太虚山雪糕正式上市，成为游客打卡必吃品，价格提升。"
      }
    ],
    "news": [
      "如何优雅而安全地庆祝？特斯拉、爱因斯坦发布最新发明。",
      "来自天命女武神的美食直播？川中名菜重现江湖，网红尝试还原菜谱。"
    ]
  },
  {
    "name": "5/1 早",
    "prices":	{
      "智慧眼罩":  20222,
      "赤鸢团子":  56,
      "潮流自热饭":  83,
      "墨镜": 92,
      "绿茶": 116,
      "二胡": 130,
      "文物玩具": 753,
      "古董花瓶": 753,
      "熊熊玩偶": 1359,
      "夜衔烛（木制）": 1239,
      "翡翠": 1567,
      "赤鸢手办": 1506,
      "辣椒": 101,
      "新型爆竹": 131
    },
    "events": [
      {
        "affect": ["新型爆竹"],
        "increase": true,
        "description": "新型爆竹上市，据说环保安全又实惠，价格提升！"
      },
      {
        "affect": ["辣椒"],
        "increase": true,
        "description": "川菜常备食材——辣椒需求量上涨，价格提升。"
      }
    ],
    "news": [
      "旅游爱好者独自探洞，意外发现神秘古代遗迹。",
      "旅游博主符华博客更新，这次是和好友的茶会记录。"
    ]
  },
  {
    "name": "5/1 晚",
    "prices":	{
      "智慧眼罩":  21777,
      "算命道具包":  67,
      "精致小盆栽":  85,
      "太虚山雪糕": 99,
      "墨镜": 86,
      "二胡": 97,
      "神州运动服": 600,
      "文物玩具": 735,
      "《职场躺平500年》": 788,
      "熊熊玩偶": 1008,
      "登山杖": 1063,
      "翡翠": 1554,
      "赤鸢团子": 115,
      "古董花瓶": 1545
    },
    "events": [
      {
        "affect": ["古董花瓶"],
        "increase": true,
        "description": "遗迹中开采出的老古董瓶照片曝光，市面上相似纹路的瓶子价格暴涨！古董花瓶价格提升。"
      },
      {
        "affect": ["赤鸢团子"],
        "increase": true,
        "description": "茶会上拍到的点心：赤鸢团子大受好评，价格提升。"
      }
    ],
    "news": [
      "突击采访企划！记者临时跟拍天命女武神的训练日常，受访者猝不及防只得轻装上阵。",
      "识之律者直播算命，连续投出七个正面，宣称接下来一周都是大晴天！"
    ]
  },
  {
    "name": "5/2 早",
    "prices":	{
      "智慧眼罩":  22444,
      "算命道具包":  39,
      "精致小盆栽":  60,
      "潮流自热饭": 72,
      "绿茶": 106,
      "二胡": 83,
      "不识时务（棉质）": 867,
      "文物玩具": 873,
      "熊熊玩偶": 1085,
      "登山杖": 1445,
      "夜衔烛（木制）": 923,
      "赤鸢手办": 1519,
      "神州运动服": 1280
    },
    "events": [
      {
        "affect": ["神州运动服"],
        "increase": true,
        "description": "被狗头朋友套上神秘运动服接受采访的新人女武神，其装扮意外走红，她的脸也很红。神州运动服价格提升。"
      },
      {
        "affect": ["算命道具包"],
        "decrease": true,
        "description": "天降暴雨，算命道具包根本不灵，价格降低。"
      }
    ],
    "news": [
      "崩坏能什么都可以做到吗？李素裳解密绝对不会迟到的传统通勤法。",
      "伏特加女孩计划大换曲风？老粉对其胡来风格感到担忧。"
    ]
  }
]
